groundhog_hpc/__init__.py
groundhog_hpc/compute.py
groundhog_hpc/console.py
groundhog_hpc/decorators.py
groundhog_hpc/errors.py
groundhog_hpc/function.py
groundhog_hpc/future.py
groundhog_hpc/harness.py
groundhog_hpc/import_hook.py
groundhog_hpc/logging.py
groundhog_hpc/serialization.py
groundhog_hpc/templating.py
groundhog_hpc/utils.py
groundhog_hpc/app/__init__.py
groundhog_hpc/app/add.py
groundhog_hpc/app/init.py
groundhog_hpc/app/main.py
groundhog_hpc/app/remove.py
groundhog_hpc/app/run.py
groundhog_hpc/app/utils.py
groundhog_hpc/configuration/__init__.py
groundhog_hpc/configuration/defaults.py
groundhog_hpc/configuration/endpoints.py
groundhog_hpc/configuration/models.py
groundhog_hpc/configuration/pep723.py
groundhog_hpc/configuration/resolver.py
groundhog_hpc/templates/groundhog_run.py.jinja
groundhog_hpc/templates/init_script.py.jinja
groundhog_hpc/templates/shell_command.sh.jinja
groundhog_hpc-0.7.2.dist-info/METADATA
groundhog_hpc-0.7.2.dist-info/WHEEL
groundhog_hpc-0.7.2.dist-info/entry_points.txt
groundhog_hpc-0.7.2.dist-info/licenses/LICENSE
groundhog_hpc-0.7.2.dist-info/RECORD
